tableau_builder/__init__.py
tableau_builder/column.py
tableau_builder/connection.py
tableau_builder/dataset.py
tableau_builder/folder.py
tableau_builder/hierarchy.py
tableau_builder/json_metadata.py
tableau_builder/metadata.py
tableau_builder/package.py
tableau_builder/tableau.py
tableau_builder-1.0.dist-info/LICENSE
tableau_builder-1.0.dist-info/METADATA
tableau_builder-1.0.dist-info/WHEEL
tableau_builder-1.0.dist-info/top_level.txt
tableau_builder-1.0.dist-info/RECORD
