Metadata-Version: 2.1
Name: tableau-builder
Version: 1.0
Summary: Programmatically build Tableau packages
Home-page: https://github.com/JiscDACT/tableau-builder
Author: scottw
Author-email: scott.wilson@jisc.ac.uk
License-File: LICENSE
Requires-Dist: pandas
Requires-Dist: lxml
Requires-Dist: openpyxl
